{
  "$schema": "",
  "type": "object",
  "definitions": {
    "authorize": {
      "$schema": "",
      "title": "Authorize",
      "description": "Authorize API",
      "strictProperties": true,
      "type": "object",
      "links": [
        {
          "description": "Authorize user to access resources",
          "href": "/api/v1/authorize",
          "method": "POST",
          "rel": "self",
          "http_header": {
            "Authorization": "Basic or Bearer XXX"
          },
          "schema": {
            "properties": {
              "Action": {
                "description": "Action applied over the resources",
                "example": "example:Read",
                "type": "string"
              },
              "Resources": {
                "description": "List of resources",
                "example": ["urn:ews:product:instance:example/resource1"],
                "type": "array",
                "items": {
                  "type": "string"
                }
              }
            },
            "required": [
              "Action",
              "Resources"
            ],
            "type": "object"
          },
          "title": "resources"
        }
      ],
      "properties": {
        "ResourcesAllowed": {
          "description": "List of allowed resources",
          "example": ["urn:ews:product:instance:example/resource1"],
          "type": "array",
          "items": {
            "type": "string"
          }
        }
      }
    }
  },
  "properties": {
    "authorize": {
      "$ref": "#/definitions/authorize"
    }
  }
}